{
  "name": "CloudSqlConnection",
  "version": "0.0.1",
  "type": "flogo:activity",
  "ref": "github.com/teshahtibco/cloudsqlsample",
  "description": "Connect to Google Cloud Sql Instance",
  "author": "Tejas Shah",
  "inputs":[
    {
      "name": "hostname",
      "type": "string"
    },
    {
      "name": "port",
      "type": "string"
    },
    {
      "name": "username",
      "type": "string"
    },
    {
      "name": "password",
      "type": "string"
    },
    {
      "name": "instance",
      "type": "string"
    }
  ],
  "outputs": [
    {
      "name": "result",
      "type": "string"
    }
  ]
}